threadpool.py
threadpool-1.3.2.dist-info/top_level.txt
threadpool-1.3.2.dist-info/RECORD
threadpool-1.3.2.dist-info/DESCRIPTION.rst
threadpool-1.3.2.dist-info/METADATA
threadpool-1.3.2.dist-info/WHEEL
threadpool-1.3.2.dist-info/metadata.json
