Metadata-Version: 1.1
Name: threadpool
Version: 1.3.2
Summary: Easy to use object-oriented thread pool framework.
Home-page: http://chrisarndt.de/projects/threadpool/
Author: Christopher Arndt
Author-email: chris@chrisarndt.de
License: MIT license
Download-URL: http://chrisarndt.de/projects/threadpool/download/
Keywords: threads,design pattern,thread pool
Platform: POSIX
Platform: Windows
Platform: MacOS X
Classifier: Development Status :: 5 - Production/Stable
Classifier: Intended Audience :: Developers
Classifier: License :: OSI Approved :: Python Software Foundation License
Classifier: Operating System :: Microsoft :: Windows
Classifier: Operating System :: POSIX
Classifier: Operating System :: MacOS :: MacOS X
Classifier: Programming Language :: Python
Classifier: Programming Language :: Python :: 2
Classifier: Programming Language :: Python :: 3
Classifier: Topic :: Software Development :: Libraries :: Python Modules
